Workbook
Name MovieData: '6-Movie Data'!$A$1:$L$1001
Name Slicer_Year_Produced: #N/A
Name Slicer_Year_Produced2: #N/A

Sheet 1-Genre Analysis
C9: Row Labels | D9: Average of Domestic Box Office | E9: Average of International Box Office | F9: Sum of Total Box Office
C10: Super Hero | D10: 2.1656334e+08 | E10: 2.6440681e+08 | F10: 23086567142
C11: Science Fiction | D11: 1.7347531e+08 | E11: 2.6903074e+08 | F11: 51330701978
C12: Fantasy | D12: 1.6256509e+08 | E12: 2.6161501e+08 | F12: 49204891330
C13: Kids Fiction | D13: 1.6224953e+08 | E13: 2.2888773e+08 | F13: 48109882439
C14: Historical Fiction | D14: 1.3209642e+08 | E14: 1.7455509e+08 | F14: 26985332964
C15: Dramatization | D15: 1.2608797e+08 | E15: 1.3278746e+08 | F15: 12943771127
C16: Contemporary Fiction | D16: 1.1517212e+08 | E16: 1.3903078e+08 | F16: 113882898770
C17: Factual | D17: 93988331 | E17: 1.0532918e+08 | F17: 1993175129
C18: Multiple Creative Types | D18: 83320000 | E18: 102034442 | F18: 185354442
C19: Grand Total | D19: 1.3988162e+08 | E19: 1.8784096e+08 | F19: 327722575321

Sheet Sheet1
A1: Row Labels | B1: Sum of Domestic Box Office | C1: Sum of International Box Office | D1: Sum of Production Budget
A2: Avatar | B2: 760507625 | C2: 2023411357 | D2: 425000000
A3: The Avengers | B3: 623279547 | C3: 896200000 | D3: 225000000
A4: Jurassic World | B4: 652188220 | C4: 1016713244 | D4: 215000000
A5: Titanic | B5: 658672302 | C5: 1548943366 | D5: 200000000
A6: The Dark Knight | B6: 533345358 | C6: 469546000 | D6: 185000000
J7: Genre | K7: Average of Domestic Box Office | L7: Average of International Box Office | M7: Sum of Total Box Office
J8: Super Hero | K8: 2.1656334e+08 | L8: 2.6440681e+08 | M8: 23086567142
D9: Row Labels | E9: Sum of Production Budget | F9: Sum of International Box Office | J9: Science Fiction | K9: 1.7347531e+08 | L9: 2.6903074e+08 | M9: 51330701978 | T9: Row Labels | U9: Average of Domestic Box Office | V9: Average of International Box Office | W9: Sum of Total Box Office
D10: Contemporary Fiction | E10: 25379119975 | F10: 62285787388 | J10: Fantasy | K10: 1.6256509e+08 | L10: 2.6161501e+08 | M10: 49204891330 | T10: Super Hero | U10: 2.1656334e+08 | V10: 2.6440681e+08 | W10: 23086567142
D11: Science Fiction | E11: 12398702619 | F11: 31207565682 | J11: Kids Fiction | K11: 1.6224953e+08 | L11: 2.2888773e+08 | M11: 48109882439 | T11: Science Fiction | U11: 1.7347531e+08 | V11: 2.6903074e+08 | W11: 51330701978
D12: Fantasy | E12: 10741838000 | F12: 30347341225 | J12: Historical Fiction | K12: 1.3209642e+08 | L12: 1.7455509e+08 | M12: 26985332964 | T12: Fantasy | U12: 1.6256509e+08 | V12: 2.6161501e+08 | W12: 49204891330
D13: Kids Fiction | E13: 10816200000 | F13: 28153190547 | J13: Dramatization | K13: 1.2608797e+08 | L13: 1.3278746e+08 | M13: 12943771127 | T13: Kids Fiction | U13: 1.6224953e+08 | V13: 2.2888773e+08 | W13: 48109882439
J14: Contemporary Fiction | K14: 1.1517212e+08 | L14: 1.3903078e+08 | M14: 113882898770 | T14: Historical Fiction | U14: 1.3209642e+08 | V14: 1.7455509e+08 | W14: 26985332964
J15: Factual | K15: 93988331 | L15: 1.0532918e+08 | M15: 1993175129 | T15: Dramatization | U15: 1.2608797e+08 | V15: 1.3278746e+08 | W15: 12943771127
J16: Multiple Creative Types | K16: 83320000 | L16: 102034442 | M16: 185354442 | T16: Contemporary Fiction | U16: 1.1517212e+08 | V16: 1.3903078e+08 | W16: 113882898770
J17: Grand Total | K17: 1.3988162e+08 | L17: 1.8784096e+08 | M17: 327722575321 | T17: Factual | U17: 93988331 | V17: 1.0532918e+08 | W17: 1993175129
T18: Multiple Creative Types | U18: 83320000 | V18: 102034442 | W18: 185354442
T19: Grand Total | U19: 1.3988162e+08 | V19: 1.8784096e+08 | W19: 327722575321
C29: Row Labels | D29: Sum of International Box Office | E29: Sum of Domestic Box Office | F29: Total
C30: Tom Cruise | D30: 3506760977 | E30: 1989993745 | F30: =GETPIVOTDATA("Sum of International Box Office",$C$29,"Lead Actor","Adam Sandler")+GETPIVOTDATA("Sum of Domestic Box Office",$C$29,"Lead Actor","Adam Sandler") -> 2385224644
C31: Johnny Depp | D31: 3177467961 | E31: 1897661308 | F31: =GETPIVOTDATA("Sum of International Box Office",$C$29,"Lead Actor","Adam Sandler")+GETPIVOTDATA("Sum of Domestic Box Office",$C$29,"Lead Actor","Adam Sandler") -> 2385224644
C32: Vin Diesel | D32: 2261888889 | E32: 941265435 | F32: =GETPIVOTDATA("Sum of International Box Office",$C$29,"Lead Actor","Adam Sandler")+GETPIVOTDATA("Sum of Domestic Box Office",$C$29,"Lead Actor","Adam Sandler") -> 2385224644
C33: Leonardo DiCaprio | D33: 2201668243 | E33: 1048426349 | F33: =GETPIVOTDATA("Sum of International Box Office",$C$29,"Lead Actor","Adam Sandler")+GETPIVOTDATA("Sum of Domestic Box Office",$C$29,"Lead Actor","Adam Sandler") -> 2385224644
C34: Dileep Rao | D34: 2023411357 | E34: 760507625 | F34: =GETPIVOTDATA("Sum of International Box Office",$C$29,"Lead Actor","Adam Sandler")+GETPIVOTDATA("Sum of Domestic Box Office",$C$29,"Lead Actor","Adam Sandler") -> 2385224644
C35: Elijah Wood | D35: 1927389895 | E35: 1035939639 | F35: =GETPIVOTDATA("Sum of International Box Office",$C$29,"Lead Actor","Adam Sandler")+GETPIVOTDATA("Sum of Domestic Box Office",$C$29,"Lead Actor","Adam Sandler") -> 2385224644
C36: Devon Murray | D36: 1804986836 | E36: 831556726 | F36: =GETPIVOTDATA("Sum of International Box Office",$C$29,"Lead Actor","Adam Sandler")+GETPIVOTDATA("Sum of Domestic Box Office",$C$29,"Lead Actor","Adam Sandler") -> 2385224644
C37: Kristen Stewart | D37: 1791857485 | E37: 1218142113 | F37: =GETPIVOTDATA("Sum of International Box Office",$C$29,"Lead Actor","Adam Sandler")+GETPIVOTDATA("Sum of Domestic Box Office",$C$29,"Lead Actor","Adam Sandler") -> 2385224644
C38: Ben Stiller | D38: 1775304616 | E38: 1457120902 | F38: =GETPIVOTDATA("Sum of International Box Office",$C$29,"Lead Actor","Adam Sandler")+GETPIVOTDATA("Sum of Domestic Box Office",$C$29,"Lead Actor","Adam Sandler") -> 2385224644
C39: Robert Downey, Jr. | D39: 1708463558 | E39: 1123473495 | F39: =GETPIVOTDATA("Sum of International Box Office",$C$29,"Lead Actor","Adam Sandler")+GETPIVOTDATA("Sum of Domestic Box Office",$C$29,"Lead Actor","Adam Sandler") -> 2385224644
C40: Josh Herdman | D40: 1617679821 | E40: 698586769 | F40: =GETPIVOTDATA("Sum of International Box Office",$C$29,"Lead Actor","Adam Sandler")+GETPIVOTDATA("Sum of Domestic Box Office",$C$29,"Lead Actor","Adam Sandler") -> 2385224644
C41: Shia LaBeouf | D41: 1594834228 | E41: 1073574219 | F41: =GETPIVOTDATA("Sum of International Box Office",$C$29,"Lead Actor","Adam Sandler")+GETPIVOTDATA("Sum of Domestic Box Office",$C$29,"Lead Actor","Adam Sandler") -> 2385224644
... C651: Grand Total | D651: 187840958459 | E651: 139881616862 | F651: =GETPIVOTDATA("Sum of International Box Office",$C$29,"Lead Actor","Adam Sandler")+GETPIVOTDATA("Sum of Domestic Box Office",$C$29,"Lead Actor","Adam Sandler") -> 2385224644
B655: Row Labels | C655: Sum of International Box Office
B656: Tom Cruise | C656: 3506760977
B657: Johnny Depp | C657: 3177467961
B658: Vin Diesel | C658: 2261888889
B659: Leonardo DiCaprio | C659: 2201668243
B660: Dileep Rao | C660: 2023411357
C675: Row Labels | D675: Sum of Production Budget | F675: Row Labels | G675: Sum of International Box Office | I675: Row Labels | J675: Sum of Domestic Box Office | L675: Row Labels | M675: Count of Best Picture Winner
C676: Johnny Depp | D676: 1682500000 | F676: Tom Cruise | G676: 3506760977 | I676: Tom Cruise | J676: 1989993745 | L676: David Patrick O'Hara | M676: 2
C677: Tom Cruise | D677: 1376000000 | F677: Johnny Depp | G677: 3177467961 | I677: Johnny Depp | J677: 1897661308 | L677: Tom Berenger | M677: 1
C678: Daniel Craig | D678: 820000000 | F678: Vin Diesel | G678: 2261888889 | I678: Ben Stiller | J678: 1457120902 | L678: Russell Crowe | M678: 1

Sheet 2-Actor Analysis
F11: Lead Actor | G11: Max of International Box Office | H11: International Box Office totals
F12: Johnny Depp | G12: 804600000 | H12: 3177467961
F13: Vin Diesel | G13: 1165213799 | H13: 2261888889
F14: Leonardo DiCaprio | G14: 1548943366 | H14: 2201668243
F15: Dileep Rao | G15: 2023411357 | H15: 2023411357
F16: Robert Downey, Jr. | G16: 806400000 | H16: 1708463558
F17: Josh Herdman | G17: 960500000 | H17: 1617679821
F18: Shia LaBeouf | G18: 771400000 | H18: 1594834228
F19: Daniel Craig | G19: 806166704 | H19: 1588448532
F20: Ellen Bry | G20: 1548943366 | H20: 1548943366
F21: Mark Wahlberg | G21: 858600000 | H21: 1537247141
F22: Chris Pratt | G22: 1016713244 | H22: 1454713244
F23: Scarlett Johansson | G23: 896200000 | H23: 1220200000
... F27: Grand Total | G27: 2023411357 | H27: 24580031840

Sheet 3-Answer Sheet
A1: ANSWER SHEET
A3: Excel has many statistical functions that are useful for answering questions about the information in data sets. Functions like COUNTIF, AVERAGEIF and SUMIF (see Manzo 7.1) provide a statistical answer for cells in a range that meet a specified criteria. There's also a set of statistical functions, the IFS's, that allow you to specify multiple crtieria (multiple conditions if needed) for a statistical computation (see Manzo 7.2). These IFS's include functions like COUNTIFS, AVERAGEIFS, SUMIFS, MAXIFS and others. For the 3 questions below write a formula (using IF or IFS functions) in the Answer column that will display the value that answers the question.
A5: Analytics Question | B5: Answer (write an Excel Formula in the space below that will display the correct value) | C5: Hints
A6: 1. How many sequels are contained in the Movie Data file? | B6: =COUNTIF('6-Movie Data'!H1:H1001,"Yes") -> 218 | C6: =COUNTIF(data range, criteria)
A7: 2. What was the total of all Production Budgets for all films produced in 2001? | B7: =SUMIF('6-Movie Data'!E1:E1001,"2001",'6-Movie Data'!L1:L1001) -> 2296500000 | C7: =SUMIF(year range, year criteria, sum range)
A8: 3. What was the highest International box office Revenue for a film that also won Best Picture? | B8: =_xlfn.MAXIFS('6-Movie Data'!J2:J1001,'6-Movie Data'!K2:K1001,"Y") -> 763562762 | C8: =MAXIFS(MAX range, criteria range, criteria)
C9: https://support.microsoft.com/en-au/office/maxifs-function-dfd611e6-da2c-488a-919b-9b6376b28883

Sheet 4-Actor Codes
A1: Actor ID | B1: Actor Name
A2: 10000 | B2: Unidentified
A3: 10015 | B3: Adam Sandler
A4: 10030 | B4: Adewale Akinnuoye-Agbaje
A5: 10045 | B5: Adolph Caesar
A6: 10060 | B6: Adrian Lester
A7: 10075 | B7: Adrienne Barbeau
A8: 10090 | B8: Al Matthews
A9: 10105 | B9: Alan Cumming
A10: 10120 | B10: Alan Tudyk
A11: 10135 | B11: Alex Hyde-White
A12: 10150 | B12: Alexa Davalos
A13: 10165 | B13: Allen Garfield
... A622: 19300 | B622: Zachary Quinto

Sheet 5-Genre Codes
A1: Genre Code | B1: Genre Desc
A2: 0 | B2: Unidentified
A3: 10 | B3: Contemporary Fiction
A4: 20 | B4: Dramatization
A5: 30 | B5: Factual
A6: 40 | B6: Fantasy
A7: 50 | B7: Historical Fiction
A8: 60 | B8: Kids Fiction
A9: 70 | B9: Multiple Creative Types
A10: 80 | B10: Science Fiction
A11: 90 | B11: Super Hero

Sheet 6-Movie Data
A1: Movie ID | B1: Movie Title | C1: Genre Code | D1: Genre | E1: Year Produced | F1: Lead Actor ID | G1: Lead Actor | H1: Sequel | I1: Domestic Box Office | J1: International Box Office | K1: Best Picture Winner | L1: Production Budget
A2: 1 | B2: Avatar | C2: 80 | D2: =VLOOKUP(C2,'5-Genre Codes'!$A$1:$B$11,2,FALSE) -> Science Fiction | E2: 2009 | F2: 12235 | G2: =VLOOKUP(F2,'4-Actor Codes'!$A$1:$B$622,2,FALSE) -> Dileep Rao | H2: No | I2: 760507625 | J2: 2023411357 | L2: 425000000
A3: 2 | B3: Titanic | C3: 50 | D3: =VLOOKUP(C3,'5-Genre Codes'!$A$1:$B$11,2,FALSE) -> Historical Fiction | E3: 1997 | F3: 15205 | G3: =VLOOKUP(F3,'4-Actor Codes'!$A$1:$B$622,2,FALSE) -> Leonardo DiCaprio | H3: No | I3: 658672302 | J3: 1548943366 | L3: 200000000
A4: 3 | B4: Jurassic World | C4: 80 | D4: =VLOOKUP(C4,'5-Genre Codes'!$A$1:$B$11,2,FALSE) -> Science Fiction | E4: 2015 | F4: 11410 | G4: =VLOOKUP(F4,'4-Actor Codes'!$A$1:$B$622,2,FALSE) -> Chris Pratt | H4: Yes | I4: 652188220 | J4: 1016713244 | L4: 215000000
A5: 4 | B5: The Avengers | C5: 90 | D5: =VLOOKUP(C5,'5-Genre Codes'!$A$1:$B$11,2,FALSE) -> Super Hero | E5: 2012 | F5: 17830 | G5: =VLOOKUP(F5,'4-Actor Codes'!$A$1:$B$622,2,FALSE) -> Scarlett Johansson | H5: No | I5: 623279547 | J5: 896200000 | L5: 225000000
A6: 5 | B6: The Dark Knight | C6: 90 | D6: =VLOOKUP(C6,'5-Genre Codes'!$A$1:$B$11,2,FALSE) -> Super Hero | E6: 2008 | F6: 11545 | G6: =VLOOKUP(F6,'4-Actor Codes'!$A$1:$B$622,2,FALSE) -> Cillian Murphy | H6: Yes | I6: 533345358 | J6: 469546000 | L6: 185000000
A7: 6 | B7: Star Wars Ep. I: The Phantom Menace | C7: 80 | D7: =VLOOKUP(C7,'5-Genre Codes'!$A$1:$B$11,2,FALSE) -> Science Fiction | E7: 1999 | F7: 10270 | G7: =VLOOKUP(F7,'4-Actor Codes'!$A$1:$B$622,2,FALSE) -> Andrew Secombe | H7: Yes | I7: 474544677 | J7: 552500000 | L7: 115000000
A8: 7 | B8: Star Wars Ep. IV: A New Hope | C8: 80 | D8: =VLOOKUP(C8,'5-Genre Codes'!$A$1:$B$11,2,FALSE) -> Science Fiction | E8: 1977 | F8: 13120 | G8: =VLOOKUP(F8,'4-Actor Codes'!$A$1:$B$622,2,FALSE) -> Harrison Ford | H8: No | I8: 460935665 | J8: 325600000 | L8: 11000000
A9: 8 | B9: The Avengers: Age of Ultron | C9: 90 | D9: =VLOOKUP(C9,'5-Genre Codes'!$A$1:$B$11,2,FALSE) -> Super Hero | E9: 2015 | F9: 11575 | G9: =VLOOKUP(F9,'4-Actor Codes'!$A$1:$B$622,2,FALSE) -> Claudia Kim | H9: Yes | I9: 459005868 | J9: 945700000 | L9: 250000000
A10: 9 | B10: The Dark Knight Rises | C10: 90 | D10: =VLOOKUP(C10,'5-Genre Codes'!$A$1:$B$11,2,FALSE) -> Super Hero | E10: 2012 | F10: 11455 | G10: =VLOOKUP(F10,'4-Actor Codes'!$A$1:$B$622,2,FALSE) -> Christian Bale | H10: Yes | I10: 448139099 | J10: 636300000 | L10: 275000000
A11: 10 | B11: Shrek 2 | C11: 60 | D11: =VLOOKUP(C11,'5-Genre Codes'!$A$1:$B$11,2,FALSE) -> Kids Fiction | E11: 2004 | F11: 16180 | G11: =VLOOKUP(F11,'4-Actor Codes'!$A$1:$B$622,2,FALSE) -> Mike Myers | H11: Yes | I11: 436471036 | J11: 495781885 | L11: 70000000
A12: 11 | B12: ET: The Extra-Terrestrial | C12: 60 | D12: =VLOOKUP(C12,'5-Genre Codes'!$A$1:$B$11,2,FALSE) -> Kids Fiction | E12: 1982 | F12: 16000 | G12: =VLOOKUP(F12,'4-Actor Codes'!$A$1:$B$622,2,FALSE) -> Michael Durrell | H12: No | I12: 434949459 | J12: 357854772 | L12: 10500000
A13: 12 | B13: The Hunger Games: Catching Fire | C13: 80 | D13: =VLOOKUP(C13,'5-Genre Codes'!$A$1:$B$11,2,FALSE) -> Science Fiction | E13: 2013 | F13: 16960 | G13: =VLOOKUP(F13,'4-Actor Codes'!$A$1:$B$622,2,FALSE) -> Philip Seymour Hoffman | H13: Yes | I13: 424668047 | J13: 440200000 | L13: 130000000
... A25: 24 | B25: Star Wars Ep. III: Revenge of the Sith | C25: 80 | D25: =VLOOKUP(C25,'5-Genre Codes'!$A$1:$B$11,2,FALSE) -> Science Fiction | E25: 2005 | F25: 13885 | G25: =VLOOKUP(F25,'4-Actor Codes'!$A$1:$B$622,2,FALSE) -> Jay Laga'aia | H25: Yes | I25: 380270577 | J25: 468728300 | L25: 115000000
A26: 25 | B26: The Lord of the Rings: The Return of the King | C26: 40 | D26: =VLOOKUP(C26,'5-Genre Codes'!$A$1:$B$11,2,FALSE) -> Fantasy | E26: 2003 | F26: 12445 | G26: =VLOOKUP(F26,'4-Actor Codes'!$A$1:$B$622,2,FALSE) -> Elijah Wood | H26: Yes | I26: 377845905 | J26: 763562762 | K26: Y | L26: 94000000
A27: 26 | B27: Spider-Man 2 | C27: 90 | D27: =VLOOKUP(C27,'5-Genre Codes'!$A$1:$B$11,2,FALSE) -> Super Hero | E27: 2004 | F27: 18685 | G27: =VLOOKUP(F27,'4-Actor Codes'!$A$1:$B$622,2,FALSE) -> Tobey Maguire | H27: Yes | I27: 373524485 | J27: 410180516 | L27: 200000000
A28: 27 | B28: The Passion of the Christ | C28: 20 | D28: =VLOOKUP(C28,'5-Genre Codes'!$A$1:$B$11,2,FALSE) -> Dramatization | E28: 2004 | F28: 13555 | G28: =VLOOKUP(F28,'4-Actor Codes'!$A$1:$B$622,2,FALSE) -> James Caviezel | H28: No | I28: 370782930 | J28: 251637737 | L28: 25000000
A29: 28 | B29: Despicable Me 2 | C29: 60 | D29: =VLOOKUP(C29,'5-Genre Codes'!$A$1:$B$11,2,FALSE) -> Kids Fiction | E29: 2013 | F29: 18205 | G29: =VLOOKUP(F29,'4-Actor Codes'!$A$1:$B$622,2,FALSE) -> Steve Carell | H29: Yes | I29: 368065385 | J29: 606808379 | L29: 76000000
A30: 29 | B30: Inside Out | C30: 60 | D30: =VLOOKUP(C30,'5-Genre Codes'!$A$1:$B$11,2,FALSE) -> Kids Fiction | E30: 2015 | F30: 15235 | G30: =VLOOKUP(F30,'4-Actor Codes'!$A$1:$B$622,2,FALSE) -> Lewis Black | H30: No | I30: 356158534 | J30: 494300000 | L30: 175000000
A31: 30 | B31: Transformers: Dark of the Moon | C31: 80 | D31: =VLOOKUP(C31,'5-Genre Codes'!$A$1:$B$11,2,FALSE) -> Science Fiction | E31: 2011 | F31: 18055 | G31: =VLOOKUP(F31,'4-Actor Codes'!$A$1:$B$622,2,FALSE) -> Shia LaBeouf | H31: Yes | I31: 352390543 | J31: 771400000 | L31: 195000000
A32: 31 | B32: Furious 7 | C32: 10 | D32: =VLOOKUP(C32,'5-Genre Codes'!$A$1:$B$11,2,FALSE) -> Contemporary Fiction | E32: 2014 | F32: 19060 | G32: =VLOOKUP(F32,'4-Actor Codes'!$A$1:$B$622,2,FALSE) -> Vin Diesel | H32: Yes | I32: 351032910 | J32: 1165213799 | L32: 190000000
A33: 32 | B33: American Sniper | C33: 20 | D33: =VLOOKUP(C33,'5-Genre Codes'!$A$1:$B$11,2,FALSE) -> Dramatization | E33: 2015 | F33: 10945 | G33: =VLOOKUP(F33,'4-Actor Codes'!$A$1:$B$622,2,FALSE) -> Bradley Cooper | H33: No | I33: 350126372 | J33: 197200000 | L33: 58000000
A34: 33 | B34: The Lord of the Rings: The Two Towers | C34: 40 | D34: =VLOOKUP(C34,'5-Genre Codes'!$A$1:$B$11,2,FALSE) -> Fantasy | E34: 2002 | F34: 12445 | G34: =VLOOKUP(F34,'4-Actor Codes'!$A$1:$B$622,2,FALSE) -> Elijah Wood | H34: Yes | I34: 342548984 | J34: 592154195 | L34: 94000000
A35: 34 | B35: The Hunger Games: Mockingjay - Part 1 | C35: 80 | D35: =VLOOKUP(C35,'5-Genre Codes'!$A$1:$B$11,2,FALSE) -> Science Fiction | E35: 2014 | F35: 13990 | G35: =VLOOKUP(F35,'4-Actor Codes'!$A$1:$B$622,2,FALSE) -> Jennifer Lawrence | H35: Yes | I35: 337135885 | J35: 372500000 | L35: 125000000
A36: 35 | B36: Spider-Man 3 | C36: 90 | D36: =VLOOKUP(C36,'5-Genre Codes'!$A$1:$B$11,2,FALSE) -> Super Hero | E36: 2007 | F36: 18685 | G36: =VLOOKUP(F36,'4-Actor Codes'!$A$1:$B$622,2,FALSE) -> Tobey Maguire | H36: Yes | I36: 336530303 | J36: 554345000 | L36: 258000000
A37: 36 | B37: Minions | C37: 60 | D37: =VLOOKUP(C37,'5-Genre Codes'!$A$1:$B$11,2,FALSE) -> Kids Fiction | E37: 2014 | F37: 14020 | G37: =VLOOKUP(F37,'4-Actor Codes'!$A$1:$B$622,2,FALSE) -> Jennifer Saunders | H37: No | I37: 335501715 | J37: 825868529 | L37: 74000000
A38: 37 | B38: Alice in Wonderland | C38: 40 | D38: =VLOOKUP(C38,'5-Genre Codes'!$A$1:$B$11,2,FALSE) -> Fantasy | E38: 2010 | F38: 12745 | G38: =VLOOKUP(F38,'4-Actor Codes'!$A$1:$B$622,2,FALSE) -> Frank Welker | H38: No | I38: 334191110 | J38: 691300000 | L38: 200000000
A39: 38 | B39: Guardians of the Galaxy | C39: 90 | D39: =VLOOKUP(C39,'5-Genre Codes'!$A$1:$B$11,2,FALSE) -> Super Hero | E39: 2014 | F39: 11410 | G39: =VLOOKUP(F39,'4-Actor Codes'!$A$1:$B$622,2,FALSE) -> Chris Pratt | H39: No | I39: 333172112 | J39: 438000000 | L39: 170000000
A40: 39 | B40: Forrest Gump | C40: 50 | D40: =VLOOKUP(C40,'5-Genre Codes'!$A$1:$B$11,2,FALSE) -> Historical Fiction | E40: 1994 | F40: 16360 | G40: =VLOOKUP(F40,'4-Actor Codes'!$A$1:$B$622,2,FALSE) -> Mykelti Williamson | H40: No | I40: 330151138 | J40: 349706026 | K40: Y | L40: 55000000
A41: 40 | B41: Shrek the Third | C41: 60 | D41: =VLOOKUP(C41,'5-Genre Codes'!$A$1:$B$11,2,FALSE) -> Kids Fiction | E41: 2007 | F41: 16180 | G41: =VLOOKUP(F41,'4-Actor Codes'!$A$1:$B$622,2,FALSE) -> Mike Myers | H41: Yes | I41: 321012359 | J41: 484610992 | L41: 160000000
A42: 41 | B42: Transformers | C42: 80 | D42: =VLOOKUP(C42,'5-Genre Codes'!$A$1:$B$11,2,FALSE) -> Science Fiction | E42: 2007 | F42: 18055 | G42: =VLOOKUP(F42,'4-Actor Codes'!$A$1:$B$622,2,FALSE) -> Shia LaBeouf | H42: No | I42: 319071806 | J42: 389026399 | L42: 151000000
A43: 42 | B43: Iron Man | C43: 90 | D43: =VLOOKUP(C43,'5-Genre Codes'!$A$1:$B$11,2,FALSE) -> Super Hero | E43: 2008 | F43: 17335 | G43: =VLOOKUP(F43,'4-Actor Codes'!$A$1:$B$622,2,FALSE) -> Robert Downey, Jr. | H43: No | I43: 318604126 | J43: 263839000 | L43: 186000000
A44: 43 | B44: Harry Potter and the Sorcerer’s Stone | C44: 40 | D44: =VLOOKUP(C44,'5-Genre Codes'!$A$1:$B$11,2,FALSE) -> Fantasy | E44: 2001 | F44: 14485 | G44: =VLOOKUP(F44,'4-Actor Codes'!$A$1:$B$622,2,FALSE) -> Josh Herdman | H44: No | I44: 317575550 | J44: 657179821 | L44: 125000000
A45: 44 | B45: Indiana Jones and the Kingdom of the Crystal Skull | C45: 50 | D45: =VLOOKUP(C45,'5-Genre Codes'!$A$1:$B$11,2,FALSE) -> Historical Fiction | E45: 2008 | F45: 14650 | G45: =VLOOKUP(F45,'4-Actor Codes'!$A$1:$B$622,2,FALSE) -> Karen Allen | H45: Yes | I45: 317023851 | J45: 469534294 | L45: 185000000
A46: 45 | B46: The Lord of the Rings: The Fellowship of the Ring | C46: 40 | D46: =VLOOKUP(C46,'5-Genre Codes'!$A$1:$B$11,2,FALSE) -> Fantasy | E46: 2001 | F46: 12445 | G46: =VLOOKUP(F46,'4-Actor Codes'!$A$1:$B$622,2,FALSE) -> Elijah Wood | H46: No | I46: 315544750 | J46: 571672938 | L46: 109000000
A47: 46 | B47: Iron Man 2 | C47: 90 | D47: =VLOOKUP(C47,'5-Genre Codes'!$A$1:$B$11,2,FALSE) -> Super Hero | E47: 2010 | F47: 13075 | G47: =VLOOKUP(F47,'4-Actor Codes'!$A$1:$B$622,2,FALSE) -> Gwyneth Paltrow | H47: Yes | I47: 312128345 | J47: 311128000 | L47: 170000000
A48: 47 | B48: Pirates of the Caribbean: At World's End | C48: 50 | D48: =VLOOKUP(C48,'5-Genre Codes'!$A$1:$B$11,2,FALSE) -> Historical Fiction | E48: 2007 | F48: 14350 | G48: =VLOOKUP(F48,'4-Actor Codes'!$A$1:$B$622,2,FALSE) -> Johnny Depp | H48: Yes | I48: 309420425 | J48: 654000000 | L48: 300000000
A49: 48 | B49: Star Wars Ep. VI: Return of the Jedi | C49: 80 | D49: =VLOOKUP(C49,'5-Genre Codes'!$A$1:$B$11,2,FALSE) -> Science Fiction | E49: 1983 | F49: 13120 | G49: =VLOOKUP(F49,'4-Actor Codes'!$A$1:$B$622,2,FALSE) -> Harrison Ford | H49: Yes | I49: 309125409 | J49: 263500000 | L49: 32500000
A50: 49 | B50: Independence Day | C50: 80 | D50: =VLOOKUP(C50,'5-Genre Codes'!$A$1:$B$11,2,FALSE) -> Science Fiction | E50: 1996 | F50: 11815 | G50: =VLOOKUP(F50,'4-Actor Codes'!$A$1:$B$622,2,FALSE) -> Dan Lauria | H50: No | I50: 306124059 | J50: 511231623 | L50: 75000000
A51: 50 | B51: Pirates of the Caribbean: The Curse of the Black Pearl | C51: 40 | D51: =VLOOKUP(C51,'5-Genre Codes'!$A$1:$B$11,2,FALSE) -> Fantasy | E51: 2003 | F51: 14350 | G51: =VLOOKUP(F51,'4-Actor Codes'!$A$1:$B$622,2,FALSE) -> Johnny Depp | H51: No | I51: 305411224 | J51: 329542879 | L51: 125000000
A52: 51 | B52: Skyfall | C52: 10 | D52: =VLOOKUP(C52,'5-Genre Codes'!$A$1:$B$11,2,FALSE) -> Contemporary Fiction | E52: 2012 | F52: 11830 | G52: =VLOOKUP(F52,'4-Actor Codes'!$A$1:$B$622,2,FALSE) -> Daniel Craig | H52: Yes | I52: 304360277 | J52: 806166704 | L52: 200000000
... A180: 179 | B180: Interstellar | C180: 80 | D180: =VLOOKUP(C180,'5-Genre Codes'!$A$1:$B$11,2,FALSE) -> Science Fiction | E180: 2014 | F180: 15805 | G180: =VLOOKUP(F180,'4-Actor Codes'!$A$1:$B$622,2,FALSE) -> Matthew McConaughey | H180: No | I180: 188017894 | J180: 477400000 | L180: 165000000
A181: 180 | B181: Gladiator | C181: 50 | D181: =VLOOKUP(C181,'5-Genre Codes'!$A$1:$B$11,2,FALSE) -> Historical Fiction | E181: 2000 | F181: 17605 | G181: =VLOOKUP(F181,'4-Actor Codes'!$A$1:$B$622,2,FALSE) -> Russell Crowe | H181: No | I181: 187683805 | J181: 270000000 | K181: Y | L181: 103000000
A182: 181 | B182: The Croods | C182: 60 | D182: =VLOOKUP(C182,'5-Genre Codes'!$A$1:$B$11,2,FALSE) -> Kids Fiction | E182: 2012 | F182: 17650 | G182: =VLOOKUP(F182,'4-Actor Codes'!$A$1:$B$622,2,FALSE) -> Ryan Reynolds | H182: No | I182: 187168425 | J182: 385900000 | L182: 135000000
A183: 182 | B183: Sherlock Holmes: A Game of Shadows | C183: 50 | D183: =VLOOKUP(C183,'5-Genre Codes'!$A$1:$B$11,2,FALSE) -> Historical Fiction | E183: 2011 | F183: 17335 | G183: =VLOOKUP(F183,'4-Actor Codes'!$A$1:$B$622,2,FALSE) -> Robert Downey, Jr. | H183: Yes | I183: 186848418 | J183: 348815025 | L183: 125000000
A184: 183 | B184: The Day After Tomorrow | C184: 80 | D184: =VLOOKUP(C184,'5-Genre Codes'!$A$1:$B$11,2,FALSE) -> Science Fiction | E184: 2004 | F184: 10060 | G184: =VLOOKUP(F184,'4-Actor Codes'!$A$1:$B$622,2,FALSE) -> Adrian Lester | H184: No | I184: 186740799 | J184: 369578651 | L184: 125000000
A185: 184 | B185: Mr. and Mrs. Smith | C185: 10 | D185: =VLOOKUP(C185,'5-Genre Codes'!$A$1:$B$11,2,FALSE) -> Contemporary Fiction | E185: 2005 | F185: 10930 | G185: =VLOOKUP(F185,'4-Actor Codes'!$A$1:$B$622,2,FALSE) -> Brad Pitt | H185: No | I185: 186336279 | J185: 299787811 | L185: 110000000
A186: 185 | B186: Snow White and the Seven Dwarfs | C186: 40 | D186: =VLOOKUP(C186,'5-Genre Codes'!$A$1:$B$11,2,FALSE) -> Fantasy | E186: 1937 | F186: 10000 | G186: =VLOOKUP(F186,'4-Actor Codes'!$A$1:$B$622,2,FALSE) -> Unidentified | H186: No | I186: 184925485 | J186: 0 | L186: 1488000
A187: 186 | B187: Batman Forever | C187: 90 | D187: =VLOOKUP(C187,'5-Genre Codes'!$A$1:$B$11,2,FALSE) -> Super Hero | E187: 1995 | F187: 14935 | G187: =VLOOKUP(F187,'4-Actor Codes'!$A$1:$B$622,2,FALSE) -> Kimberly Scott | H187: Yes | I187: 183997904 | J187: 152498032 | L187: 100000000
A188: 187 | B188: Pitch Perfect 2 | C188: 10 | D188: =VLOOKUP(C188,'5-Genre Codes'!$A$1:$B$11,2,FALSE) -> Contemporary Fiction | E188: 2014 | F188: 10390 | G188: =VLOOKUP(F188,'4-Actor Codes'!$A$1:$B$622,2,FALSE) -> Anna Kendrick | H188: Yes | I188: 183785415 | J188: 102847847 | L188: 29000000
A189: 188 | B189: Ocean's Eleven | C189: 10 | D189: =VLOOKUP(C189,'5-Genre Codes'!$A$1:$B$11,2,FALSE) -> Contemporary Fiction | E189: 2001 | F189: 12925 | G189: =VLOOKUP(F189,'4-Actor Codes'!$A$1:$B$622,2,FALSE) -> George Clooney | H189: No | I189: 183417150 | J189: 267311379 | L189: 85000000
A190: 189 | B190: The Simpsons Movie | C190: 10 | D190: =VLOOKUP(C190,'5-Genre Codes'!$A$1:$B$11,2,FALSE) -> Contemporary Fiction | E190: 2007 | F190: 11785 | G190: =VLOOKUP(F190,'4-Actor Codes'!$A$1:$B$622,2,FALSE) -> Dan Castellaneta | H190: No | I190: 183135014 | J190: 343936008 | L190: 72500000
A191: 190 | B191: What Women Want | C191: 10 | D191: =VLOOKUP(C191,'5-Genre Codes'!$A$1:$B$11,2,FALSE) -> Contemporary Fiction | E191: 2000 | F191: 15865 | G191: =VLOOKUP(F191,'4-Actor Codes'!$A$1:$B$622,2,FALSE) -> Mel Gibson | H191: No | I191: 182805123 | J191: 191300000 | L191: 65000000
A192: 191 | B192: The Perfect Storm | C192: 20 | D192: =VLOOKUP(C192,'5-Genre Codes'!$A$1:$B$11,2,FALSE) -> Dramatization | E192: 2000 | F192: 12925 | G192: =VLOOKUP(F192,'4-Actor Codes'!$A$1:$B$622,2,FALSE) -> George Clooney | H192: No | I192: 182618434 | J192: 146093000 | L192: 120000000
A193: 192 | B193: Lincoln | C193: 20 | D193: =VLOOKUP(C193,'5-Genre Codes'!$A$1:$B$11,2,FALSE) -> Dramatization | E193: 2011 | F193: 11845 | G193: =VLOOKUP(F193,'4-Actor Codes'!$A$1:$B$622,2,FALSE) -> Daniel Day-Lewis | H193: No | I193: 182207973 | J193: 91138308 | L193: 65000000
... A227: 226 | B227: True Grit | C227: 50 | D227: =VLOOKUP(C227,'5-Genre Codes'!$A$1:$B$11,2,FALSE) -> Historical Fiction | E227: 2010 | F227: 13915 | G227: =VLOOKUP(F227,'4-Actor Codes'!$A$1:$B$622,2,FALSE) -> Jeff Bridges | H227: No | I227: 171050328 | J227: 81033923 | L227: 35000000
A228: 227 | B228: A Beautiful Mind | C228: 20 | D228: =VLOOKUP(C228,'5-Genre Codes'!$A$1:$B$11,2,FALSE) -> Dramatization | E228: 2001 | F228: 17500 | G228: =VLOOKUP(F228,'4-Actor Codes'!$A$1:$B$622,2,FALSE) -> Ron Howard | H228: No | I228: 170708996 | J228: 146959062 | K228: Y | L228: 78000000
A229: 228 | B229: Chicago | C229: 50 | D229: =VLOOKUP(C229,'5-Genre Codes'!$A$1:$B$11,2,FALSE) -> Historical Fiction | E229: 2002 | F229: 11335 | G229: =VLOOKUP(F229,'4-Actor Codes'!$A$1:$B$622,2,FALSE) -> Chita Rivera | H229: No | I229: 170687518 | J229: 137000000 | L229: 30000000
A230: 229 | B230: Home Alone 2: Lost in New York | C230: 10 | D230: =VLOOKUP(C230,'5-Genre Codes'!$A$1:$B$11,2,FALSE) -> Contemporary Fiction | E230: 1992 | F230: 17200 | G230: =VLOOKUP(F230,'4-Actor Codes'!$A$1:$B$622,2,FALSE) -> Rip Taylor | H230: Yes | I230: 170004045 | J230: 185409334 | L230: 20000000
A231: 230 | B231: The Help | C231: 50 | D231: =VLOOKUP(C231,'5-Genre Codes'!$A$1:$B$11,2,FALSE) -> Historical Fiction | E231: 2010 | F231: 12520 | G231: =VLOOKUP(F231,'4-Actor Codes'!$A$1:$B$622,2,FALSE) -> Emma Stone | H231: No | I231: 169705587 | J231: 43414417 | L231: 25000000
A232: 231 | B232: Quantum of Solace | C232: 10 | D232: =VLOOKUP(C232,'5-Genre Codes'!$A$1:$B$11,2,FALSE) -> Contemporary Fiction | E232: 2008 | F232: 11830 | G232: =VLOOKUP(F232,'4-Actor Codes'!$A$1:$B$622,2,FALSE) -> Daniel Craig | H232: Yes | I232: 169368427 | J232: 422323651 | L232: 230000000
A233: 232 | B233: Bridesmaids | C233: 10 | D233: =VLOOKUP(C233,'5-Genre Codes'!$A$1:$B$11,2,FALSE) -> Contemporary Fiction | E233: 2011 | F233: 15025 | G233: =VLOOKUP(F233,'4-Actor Codes'!$A$1:$B$622,2,FALSE) -> Kristen Wiig | H233: No | I233: 169106725 | J233: 120420305 | L233: 32500000
A234: 233 | B234: Wild Hogs | C234: 10 | D234: =VLOOKUP(C234,'5-Genre Codes'!$A$1:$B$11,2,FALSE) -> Contemporary Fiction | E234: 2007 | F234: 14320 | G234: =VLOOKUP(F234,'4-Actor Codes'!$A$1:$B$622,2,FALSE) -> John Travolta | H234: No | I234: 168213584 | J234: 84800000 | L234: 0
A235: 234 | B235: Crocodile Dundee | C235: 10 | D235: =VLOOKUP(C235,'5-Genre Codes'!$A$1:$B$11,2,FALSE) -> Contemporary Fiction | E235: 1986 | F235: 15310 | G235: =VLOOKUP(F235,'4-Actor Codes'!$A$1:$B$622,2,FALSE) -> Linda Kozlowski | H235: No | I235: 168134511 | J235: 153400000 | L235: 8800000
A236: 235 | B236: Rain Man | C236: 10 | D236: =VLOOKUP(C236,'5-Genre Codes'!$A$1:$B$11,2,FALSE) -> Contemporary Fiction | E236: 1988 | F236: 18745 | G236: =VLOOKUP(F236,'4-Actor Codes'!$A$1:$B$622,2,FALSE) -> Tom Cruise | H236: No | I236: 168106313 | J236: 239974565 | K236: Y | L236: 25000000
A237: 236 | B237: Gone Girl | C237: 10 | D237: =VLOOKUP(C237,'5-Genre Codes'!$A$1:$B$11,2,FALSE) -> Contemporary Fiction | E237: 2014 | F237: 10630 | G237: =VLOOKUP(F237,'4-Actor Codes'!$A$1:$B$622,2,FALSE) -> Ben Affleck | H237: No | I237: 167767189 | J237: 200800000 | L237: 61000000
A238: 237 | B238: Casino Royale | C238: 10 | D238: =VLOOKUP(C238,'5-Genre Codes'!$A$1:$B$11,2,FALSE) -> Contemporary Fiction | E238: 2006 | F238: 13360 | G238: =VLOOKUP(F238,'4-Actor Codes'!$A$1:$B$622,2,FALSE) -> Ivana Milicevic | H238: Yes | I238: 167220102 | J238: 427055283 | L238: 102000000
A239: 238 | B239: Meet the Parents | C239: 10 | D239: =VLOOKUP(C239,'5-Genre Codes'!$A$1:$B$11,2,FALSE) -> Contemporary Fiction | E239: 2000 | F239: 10660 | G239: =VLOOKUP(F239,'4-Actor Codes'!$A$1:$B$622,2,FALSE) -> Ben Stiller | H239: No | I239: 166225040 | J239: 138374859 | L239: 55000000
A240: 239 | B240: Fifty Shades of Grey | C240: 10 | D240: =VLOOKUP(C240,'5-Genre Codes'!$A$1:$B$11,2,FALSE) -> Contemporary Fiction | E240: 2013 | F240: 11725 | G240: =VLOOKUP(F240,'4-Actor Codes'!$A$1:$B$622,2,FALSE) -> Dakota Johnson | H240: No | I240: 166167230 | J240: 404288027 | L240: 40000000
A241: 240 | B241: 2012 | C241: 80 | D241: =VLOOKUP(C241,'5-Genre Codes'!$A$1:$B$11,2,FALSE) -> Science Fiction | E241: 2009 | F241: 11275 | G241: =VLOOKUP(F241,'4-Actor Codes'!$A$1:$B$622,2,FALSE) -> Chang Tseng | H241: No | I241: 166112167 | J241: 622296372 | L241: 200000000
A242: 241 | B242: Close Encounters of the Third Kind | C242: 80 | D242: =VLOOKUP(C242,'5-Genre Codes'!$A$1:$B$11,2,FALSE) -> Science Fiction | E242: 1977 | F242: 15880 | G242: =VLOOKUP(F242,'4-Actor Codes'!$A$1:$B$622,2,FALSE) -> Melinda Dillon | H242: No | I242: 166000000 | J242: 171700000 | L242: 20000000
A243: 242 | B243: Hotel Transylvania 2 | C243: 60 | D243: =VLOOKUP(C243,'5-Genre Codes'!$A$1:$B$11,2,FALSE) -> Kids Fiction | E243: 2015 | F243: 10015 | G243: =VLOOKUP(F243,'4-Actor Codes'!$A$1:$B$622,2,FALSE) -> Adam Sandler | H243: Yes | I243: 165447891 | J243: 242900000 | L243: 80000000
A244: 243 | B244: Robin Hood: Prince of Thieves | C244: 50 | D244: =VLOOKUP(C244,'5-Genre Codes'!$A$1:$B$11,2,FALSE) -> Historical Fiction | E244: 1991 | F244: 15640 | G244: =VLOOKUP(F244,'4-Actor Codes'!$A$1:$B$622,2,FALSE) -> Mary Elizabeth Mastrantonio | H244: No | I244: 165360108 | J244: 225006092 | L244: 50000000
A245: 244 | B245: Kung Fu Panda 2 | C245: 60 | D245: =VLOOKUP(C245,'5-Genre Codes'!$A$1:$B$11,2,FALSE) -> Kids Fiction | E245: 2011 | F245: 12325 | G245: =VLOOKUP(F245,'4-Actor Codes'!$A$1:$B$622,2,FALSE) -> Dustin Hoffman | H245: Yes | I245: 165249063 | J245: 499588484 | L245: 150000000
A246: 245 | B246: Hannibal | C246: 10 | D246: =VLOOKUP(C246,'5-Genre Codes'!$A$1:$B$11,2,FALSE) -> Contemporary Fiction | E246: 2001 | F246: 14500 | G246: =VLOOKUP(F246,'4-Actor Codes'!$A$1:$B$622,2,FALSE) -> Judie Aronson | H246: No | I246: 165091986 | J246: 185008014 | L246: 87000000
A247: 246 | B247: Catch Me if You Can | C247: 20 | D247: =VLOOKUP(C247,'5-Genre Codes'!$A$1:$B$11,2,FALSE) -> Dramatization | E247: 2002 | F247: 10135 | G247: =VLOOKUP(F247,'4-Actor Codes'!$A$1:$B$622,2,FALSE) -> Alex Hyde-White | H247: No | I247: 164606800 | J247: 191005491 | L247: 52000000
A248: 247 | B248: 3 Men and a Baby | C248: 10 | D248: =VLOOKUP(C248,'5-Genre Codes'!$A$1:$B$11,2,FALSE) -> Contemporary Fiction | E248: 1987 | F248: 12130 | G248: =VLOOKUP(F248,'4-Actor Codes'!$A$1:$B$622,2,FALSE) -> Derek de Lint | H248: No | I248: 164016972 | J248: 0 | L248: 15000000
... A251: 250 | B251: Clash of the Titans | C251: 40 | D251: =VLOOKUP(C251,'5-Genre Codes'!$A$1:$B$11,2,FALSE) -> Fantasy | E251: 2010 | F251: 10150 | G251: =VLOOKUP(F251,'4-Actor Codes'!$A$1:$B$622,2,FALSE) -> Alexa Davalos | H251: No | I251: 163214888 | J251: 330000000 | L251: 125000000
A252: 251 | B252: The Sound of Music | C252: 50 | D252: =VLOOKUP(C252,'5-Genre Codes'!$A$1:$B$11,2,FALSE) -> Historical Fiction | E252: 1965 | F252: 11515 | G252: =VLOOKUP(F252,'4-Actor Codes'!$A$1:$B$622,2,FALSE) -> Christopher Plummer | H252: No | I252: 163214286 | J252: 123000000 | K252: Y | L252: 8200000
A253: 252 | B253: The SpongeBob Movie: Sponge Out of Water | C253: 60 | D253: =VLOOKUP(C253,'5-Genre Codes'!$A$1:$B$11,2,FALSE) -> Kids Fiction | E253: 2014 | F253: 10765 | G253: =VLOOKUP(F253,'4-Actor Codes'!$A$1:$B$622,2,FALSE) -> Bill Fagerbakke | H253: No | I253: 162994032 | J253: 148600000 | L253: 74000000
A254: 253 | B254: Batman Returns | C254: 90 | D254: =VLOOKUP(C254,'5-Genre Codes'!$A$1:$B$11,2,FALSE) -> Super Hero | E254: 1992 | F254: 11005 | G254: =VLOOKUP(F254,'4-Actor Codes'!$A$1:$B$622,2,FALSE) -> Branscombe Richmond | H254: Yes | I254: 162833635 | J254: 103990656 | L254: 80000000
A255: 254 | B255: Django Unchained | C255: 50 | D255: =VLOOKUP(C255,'5-Genre Codes'!$A$1:$B$11,2,FALSE) -> Historical Fiction | E255: 2011 | F255: 13735 | G255: =VLOOKUP(F255,'4-Actor Codes'!$A$1:$B$622,2,FALSE) -> Jamie Foxx | H255: No | I255: 162805434 | J255: 262568254 | L255: 100000000
A256: 255 | B256: A Bug's Life | C256: 40 | D256: =VLOOKUP(C256,'5-Genre Codes'!$A$1:$B$11,2,FALSE) -> Fantasy | E256: 1998 | F256: 10780 | G256: =VLOOKUP(F256,'4-Actor Codes'!$A$1:$B$622,2,FALSE) -> Bill Farmer | H256: No | I256: 162792677 | J256: 200296754 | L256: 45000000
A257: 256 | B257: The Pursuit of Happyness | C257: 20 | D257: =VLOOKUP(C257,'5-Genre Codes'!$A$1:$B$11,2,FALSE) -> Dramatization | E257: 2006 | F257: 19165 | G257: =VLOOKUP(F257,'4-Actor Codes'!$A$1:$B$622,2,FALSE) -> Will Smith | H257: No | I257: 162586036 | J257: 144739597 | L257: 55000000
A258: 257 | B258: Grown Ups | C258: 10 | D258: =VLOOKUP(C258,'5-Genre Codes'!$A$1:$B$11,2,FALSE) -> Contemporary Fiction | E258: 2010 | F258: 13720 | G258: =VLOOKUP(F258,'4-Actor Codes'!$A$1:$B$622,2,FALSE) -> Jamie Chung | H258: No | I258: 162001186 | J258: 110222244 | L258: 75000000
A259: 258 | B259: The Waterboy | C259: 10 | D259: =VLOOKUP(C259,'5-Genre Codes'!$A$1:$B$11,2,FALSE) -> Contemporary Fiction | E259: 1998 | F259: 10015 | G259: =VLOOKUP(F259,'4-Actor Codes'!$A$1:$B$622,2,FALSE) -> Adam Sandler | H259: No | I259: 161487252 | J259: 28700000 | L259: 23000000
A260: 259 | B260: Shark Tale | C260: 60 | D260: =VLOOKUP(C260,'5-Genre Codes'!$A$1:$B$11,2,FALSE) -> Kids Fiction | E260: 2004 | F260: 19165 | G260: =VLOOKUP(F260,'4-Actor Codes'!$A$1:$B$622,2,FALSE) -> Will Smith | H260: No | I260: 161412000 | J260: 210505043 | L260: 75000000
A261: 260 | B261: Ice Age: Continental Drift | C261: 40 | D261: =VLOOKUP(C261,'5-Genre Codes'!$A$1:$B$11,2,FALSE) -> Fantasy | E261: 2012 | F261: 17080 | G261: =VLOOKUP(F261,'4-Actor Codes'!$A$1:$B$622,2,FALSE) -> Ray Romano | H261: Yes | I261: 161321843 | J261: 718443294 | L261: 95000000
A262: 261 | B262: Straight Outta Compton | C262: 20 | D262: =VLOOKUP(C262,'5-Genre Codes'!$A$1:$B$11,2,FALSE) -> Dramatization | E262: 2015 | F262: 16600 | G262: =VLOOKUP(F262,'4-Actor Codes'!$A$1:$B$622,2,FALSE) -> O'Shea Jackson, Jr. | H262: No | I262: 161058685 | J262: 38963601 | L262: 28000000
A263: 262 | B263: Die Another Day | C263: 10 | D263: =VLOOKUP(C263,'5-Genre Codes'!$A$1:$B$11,2,FALSE) -> Contemporary Fiction | E263: 2002 | F263: 15430 | G263: =VLOOKUP(F263,'4-Actor Codes'!$A$1:$B$622,2,FALSE) -> Madonna | H263: Yes | I263: 160932247 | J263: 271000000 | L263: 142000000
A264: 263 | B264: The Sting | C264: 50 | D264: =VLOOKUP(C264,'5-Genre Codes'!$A$1:$B$11,2,FALSE) -> Historical Fiction | E264: 1973 | F264: 16780 | G264: =VLOOKUP(F264,'4-Actor Codes'!$A$1:$B$622,2,FALSE) -> Paul Newman | H264: No | I264: 159616327 | J264: 0 | K264: Y | L264: 5500000
A265: 264 | B265: The Heat | C265: 10 | D265: =VLOOKUP(C265,'5-Genre Codes'!$A$1:$B$11,2,FALSE) -> Contemporary Fiction | E265: 2013 | F265: 17770 | G265: =VLOOKUP(F265,'4-Actor Codes'!$A$1:$B$622,2,FALSE) -> Sandra Bullock | H265: No | I265: 159581587 | J265: 70146187 | L265: 43000000
A266: 265 | B266: The Firm | C266: 10 | D266: =VLOOKUP(C266,'5-Genre Codes'!$A$1:$B$11,2,FALSE) -> Contemporary Fiction | E266: 1993 | F266: 18700 | G266: =VLOOKUP(F266,'4-Actor Codes'!$A$1:$B$622,2,FALSE) -> Tobin Bell | H266: No | I266: 158340892 | J266: 112000000 | L266: 42000000
A267: 266 | B267: The Longest Yard | C267: 10 | D267: =VLOOKUP(C267,'5-Genre Codes'!$A$1:$B$11,2,FALSE) -> Contemporary Fiction | E267: 2005 | F267: 10015 | G267: =VLOOKUP(F267,'4-Actor Codes'!$A$1:$B$622,2,FALSE) -> Adam Sandler | H267: No | I267: 158119460 | J267: 32201108 | L267: 82000000
A268: 267 | B268: X-Men | C268: 90 | D268: =VLOOKUP(C268,'5-Genre Codes'!$A$1:$B$11,2,FALSE) -> Super Hero | E268: 2000 | F268: 16660 | G268: =VLOOKUP(F268,'4-Actor Codes'!$A$1:$B$622,2,FALSE) -> Patrick Stewart | H268: No | I268: 157299717 | J268: 284000000 | L268: 165000000
A269: 268 | B269: Scary Movie | C269: 10 | D269: =VLOOKUP(C269,'5-Genre Codes'!$A$1:$B$11,2,FALSE) -> Contemporary Fiction | E269: 2000 | F269: 17950 | G269: =VLOOKUP(F269,'4-Actor Codes'!$A$1:$B$622,2,FALSE) -> Shannon Elizabeth | H269: No | I269: 157019771 | J269: 120180229 | L269: 19000000
A270: 269 | B270: What Lies Beneath | C270: 10 | D270: =VLOOKUP(C270,'5-Genre Codes'!$A$1:$B$11,2,FALSE) -> Contemporary Fiction | E270: 2000 | F270: 13120 | G270: =VLOOKUP(F270,'4-Actor Codes'!$A$1:$B$622,2,FALSE) -> Harrison Ford | H270: No | I270: 155370362 | J270: 133229638 | L270: 90000000
A271: 270 | B271: The Mummy | C271: 40 | D271: =VLOOKUP(C271,'5-Genre Codes'!$A$1:$B$11,2,FALSE) -> Fantasy | E271: 1999 | F271: 11035 | G271: =VLOOKUP(F271,'4-Actor Codes'!$A$1:$B$622,2,FALSE) -> Brendan Fraser | H271: No | I271: 155247825 | J271: 261000000 | L271: 80000000
A272: 271 | B272: San Andreas | C272: 80 | D272: =VLOOKUP(C272,'5-Genre Codes'!$A$1:$B$11,2,FALSE) -> Science Fiction | E272: 2015 | F272: 12355 | G272: =VLOOKUP(F272,'4-Actor Codes'!$A$1:$B$622,2,FALSE) -> Dwayne Johnson | H272: No | I272: 155190832 | J272: 314400000 | L272: 110000000
A273: 272 | B273: Snow White and the Huntsman | C273: 40 | D273: =VLOOKUP(C273,'5-Genre Codes'!$A$1:$B$11,2,FALSE) -> Fantasy | E273: 2011 | F273: 15010 | G273: =VLOOKUP(F273,'4-Actor Codes'!$A$1:$B$622,2,FALSE) -> Kristen Stewart | H273: No | I273: 155136755 | J273: 245880169 | L273: 170000000
...
